saber/__init__.py
saber/groups.py
saber/main.py
saber/pretrained_weights.py
saber/analysis/__init__.py
saber/analysis/analysis_cli.py
saber/analysis/organelle_statistics.py
saber/analysis/refine_membranes.py
saber/classifier/__init__.py
saber/classifier/cli.py
saber/classifier/evaluator.py
saber/classifier/fabric_trainer.py
saber/classifier/inference.py
saber/classifier/train.py
saber/classifier/trainer.py
saber/classifier/datasets/RandMaskCrop.py
saber/classifier/datasets/__init__.py
saber/classifier/datasets/augment.py
saber/classifier/datasets/multiZarrDataset.py
saber/classifier/datasets/rgb_augment.py
saber/classifier/datasets/singleZarrDataset.py
saber/classifier/models/ConvNeXt.py
saber/classifier/models/SAM2.py
saber/classifier/models/SwinTransformer.py
saber/classifier/models/__init__.py
saber/classifier/models/common.py
saber/classifier/models/predictor.py
saber/classifier/preprocess/__init__.py
saber/classifier/preprocess/apply_labels.py
saber/classifier/preprocess/micro_prep.py
saber/classifier/preprocess/slurm.py
saber/classifier/preprocess/split_merge_data.py
saber/classifier/preprocess/tomo_prep.py
saber/classifier/preprocess/training_data_info.py
saber/entry_points/__init__.py
saber/entry_points/inference_core.py
saber/entry_points/run_analysis.py
saber/entry_points/run_fib_segment.py
saber/entry_points/run_light_segment.py
saber/entry_points/run_membrane_refinement.py
saber/entry_points/run_micrograph_segment.py
saber/entry_points/run_tomogram_segment.py
saber/entry_points/segment_methods.py
saber/entry_points/slurm.py
saber/filters/__init__.py
saber/filters/downsample.py
saber/filters/estimate_thickness.py
saber/filters/gaussian.py
saber/filters/masks.py
saber/filters/tomograms.py
saber/gui/__init__.py
saber/gui/inspection.ipynb
saber/gui/run.py
saber/gui/base/__init__.py
saber/gui/base/annotation_viewer.py
saber/gui/base/annotation_viewer_3d.py
saber/gui/base/multi_class_segmentation_picker.py
saber/gui/base/segmentation_picker.py
saber_em-0.10.0.dist-info/METADATA
saber_em-0.10.0.dist-info/WHEEL
saber_em-0.10.0.dist-info/entry_points.txt
saber_em-0.10.0.dist-info/licenses/LICENSE
saber_em-0.10.0.dist-info/RECORD
