Metadata-Version: 2.4
Name: saber-em
Version: 0.10.0
Summary: Segment Anything Based Electron Recognition
Project-URL: Homepage, https://github.com/czi-ai/saber
Project-URL: Documentation, http://chanzuckerberg.github.io/saber/
Project-URL: Issues, https://github.com/czi-ai/saber/issues
License: MIT License
License-File: LICENSE
Classifier: License :: OSI Approved :: MIT License
Classifier: Programming Language :: Python :: 3.10
Classifier: Programming Language :: Python :: 3.11
Classifier: Programming Language :: Python :: 3.12
Classifier: Programming Language :: Python :: 3.13
Classifier: Topic :: Scientific/Engineering :: Artificial Intelligence
Classifier: Topic :: Scientific/Engineering :: Image Processing
Classifier: Topic :: Scientific/Engineering :: Image Recognition
Requires-Python: >=3.10
Requires-Dist: copick
Requires-Dist: copick-utils
Requires-Dist: flask
Requires-Dist: flask-cors
Requires-Dist: ipywidgets
Requires-Dist: kornia
Requires-Dist: matplotlib
Requires-Dist: monai
Requires-Dist: mrcfile
Requires-Dist: multiprocess
Requires-Dist: nibabel
Requires-Dist: opencv-python
Requires-Dist: rich-click
Requires-Dist: sam2
Requires-Dist: scikit-learn
Requires-Dist: starfile
Requires-Dist: torch-ema
Requires-Dist: torchmetrics
Requires-Dist: tqdm
Provides-Extra: gui
Requires-Dist: pyqt5; extra == 'gui'
Requires-Dist: pyqtgraph; extra == 'gui'
Provides-Extra: materials
Requires-Dist: hyperspy; extra == 'materials'
